llmpy_models/__init__.py
llmpy_models/llmpy_models.py
llmpy_models-0.0.19.dist-info/METADATA
llmpy_models-0.0.19.dist-info/WHEEL
llmpy_models-0.0.19.dist-info/licenses/LICENSE.txt
llmpy_models-0.0.19.dist-info/RECORD
